gvc4fastq/SOAPnuke.py
gvc4fastq/__init__.py
gvc4fastq/bwa_samtools.py
gvc4fastq/fastq_vcf_pipeline.py
gvc4fastq/sortbamInterface.py
gvc4fastq/tb_pipeline.py
gvc4fastq-1.0.15.data/scripts/check_runtime.py
gvc4fastq-1.0.15.data/scripts/fastq_vcf.py
gvc4fastq-1.0.15.dist-info/LICENSE
gvc4fastq-1.0.15.dist-info/METADATA
gvc4fastq-1.0.15.dist-info/WHEEL
gvc4fastq-1.0.15.dist-info/top_level.txt
gvc4fastq-1.0.15.dist-info/RECORD
