Metadata-Version: 2.1
Name: gvc4fastq
Version: 1.0.15
Summary: GVC4FASTQ is a data processing pipeline developed by Genome Wisdom Inc. GVC4FASTQ detects germline and somatic mutations (SNV, InDel, SV) from FASTQ files.
Home-page: UNKNOWN
Author: LongHui.Yin
Author-email: dragonfly.yin@genowis.com
License: UNKNOWN
Platform: UNKNOWN
Classifier: Programming Language :: Python :: 2.7
Classifier: License :: Free For Educational Use
Requires-Python: <3
Requires-Dist: gvc4bam (>=1.0.8)
Requires-Dist: docker (==2.5.1)
Requires-Dist: pysam
Requires-Dist: toil
Requires-Dist: toil-runner
